elsciRL/__init__.py
elsciRL/config.py
elsciRL/config_local.py
elsciRL/GUI/app.py
elsciRL/GUI/prerender.py
elsciRL/GUI/prerender_encoder.py
elsciRL/GUI/static/app_setup.md
elsciRL/GUI/static/styles.css
elsciRL/GUI/templates/_generic_agent_param_form.html
elsciRL/GUI/templates/index.html
elsciRL/adapters/__init__.py
elsciRL/adapters/LLM_state_generators/base_prompt.py
elsciRL/adapters/LLM_state_generators/text_gpt-4.1.py
elsciRL/adapters/LLM_state_generators/text_ollama.py
elsciRL/agents/DQN.py
elsciRL/agents/__init__.py
elsciRL/agents/agent_abstract.py
elsciRL/agents/random_agent.py
elsciRL/agents/table_q_agent.py
elsciRL/agents/LLM_agents/ollama_agent.py
elsciRL/agents/stable_baselines/SB3_A2C.py
elsciRL/agents/stable_baselines/SB3_DQN.py
elsciRL/agents/stable_baselines/SB3_PPO.py
elsciRL/analysis/combined_tabular_results.py
elsciRL/analysis/combined_variance_visual.py
elsciRL/analysis/convergence_measure.py
elsciRL/analysis/tabular_output.py
elsciRL/analysis/visual_output.py
elsciRL/application_suite/experiment_agent.py
elsciRL/application_suite/import_data.py
elsciRL/application_suite/import_tool.py
elsciRL/application_suite/search_agent.py
elsciRL/encoders/__init__.py
elsciRL/encoders/encoder_abstract.py
elsciRL/encoders/observable_objects_encoded.py
elsciRL/encoders/poss_actions_encoded.py
elsciRL/encoders/poss_state_encoded.py
elsciRL/encoders/prior_actions_encoded.py
elsciRL/encoders/language_transformers/MiniLM_L6v2.py
elsciRL/environment_setup/elsciRL_info.py
elsciRL/environment_setup/gym_translator.py
elsciRL/environment_setup/gym_wrapper_abstract.py
elsciRL/environment_setup/imports.py
elsciRL/environment_setup/instruction_reward_wrapper.py
elsciRL/environment_setup/results_table.py
elsciRL/evaluation/standard_report.py
elsciRL/examples/DemoExperiment.py
elsciRL/examples/experiment_config.py
elsciRL/examples/adapters/elsciRL_sailing_default.py
elsciRL/examples/adapters/elsciRL_sailing_language.py
elsciRL/examples/adapters/gym_frozenlake_default.py
elscirl-0.4.0.dist-info/licenses/LICENSE
elscirl-0.4.0.dist-info/METADATA
elscirl-0.4.0.dist-info/WHEEL
elscirl-0.4.0.dist-info/top_level.txt
elscirl-0.4.0.dist-info/RECORD
