Metadata-Version: 2.4
Name: elsciRL
Version: 0.4.0
Summary: Apply language solutions to Reinforcement Learning problems.
Home-page: https://github.com/pdfosborne/elsciRL
Author: Philip Osborne
Author-email: pdfosborne@gmail.com
License: Apache-2.0 license
License-File: LICENSE
Requires-Dist: numpy
Requires-Dist: pandas
Requires-Dist: matplotlib
Requires-Dist: seaborn
Requires-Dist: scipy>=1.10.1
Requires-Dist: torch
Requires-Dist: tqdm
Requires-Dist: httpimport
Requires-Dist: sentence-transformers
Requires-Dist: gymnasium
Requires-Dist: stable-baselines3
Requires-Dist: flask
Requires-Dist: ollama
Requires-Dist: markdown
Dynamic: author
Dynamic: author-email
Dynamic: home-page
Dynamic: license
Dynamic: license-file
Dynamic: requires-dist
Dynamic: summary
